birdhousebuilder.recipe.pywps-0.9.0-py2.7-nspkg.pth
birdhousebuilder/recipe/pywps/README.txt
birdhousebuilder/recipe/pywps/__init__.py
birdhousebuilder/recipe/pywps/gunicorn.conf_py
birdhousebuilder/recipe/pywps/nginx-default.conf
birdhousebuilder/recipe/pywps/nginx.conf
birdhousebuilder/recipe/pywps/pywps.cfg
birdhousebuilder/recipe/pywps/runwps.sh
birdhousebuilder/recipe/pywps/wpsapp_py
birdhousebuilder/recipe/pywps/tests/__init__.py
birdhousebuilder/recipe/pywps/tests/test_doctests.py
birdhousebuilder/recipe/pywps/tests/test_unit.py
birdhousebuilder.recipe.pywps-0.9.0.dist-info/DESCRIPTION.rst
birdhousebuilder.recipe.pywps-0.9.0.dist-info/METADATA
birdhousebuilder.recipe.pywps-0.9.0.dist-info/RECORD
birdhousebuilder.recipe.pywps-0.9.0.dist-info/WHEEL
birdhousebuilder.recipe.pywps-0.9.0.dist-info/entry_points.txt
birdhousebuilder.recipe.pywps-0.9.0.dist-info/metadata.json
birdhousebuilder.recipe.pywps-0.9.0.dist-info/namespace_packages.txt
birdhousebuilder.recipe.pywps-0.9.0.dist-info/top_level.txt
