Metadata-Version: 2.0
Name: birdhousebuilder.recipe.pywps
Version: 0.9.0
Summary: A Buildout recipe to install and configure PyWPS Web Processing Service with conda.
Home-page: https://github.com/bird-house/birdhousebuilder.recipe.pywps
Author: Birdhouse
Author-email: wps-dev@dkrz.de
License: Apache License 2
Keywords: buildout recipe pywps wps birdhouse conda
Platform: UNKNOWN
Classifier: Framework :: Buildout
Classifier: Intended Audience :: Developers
Classifier: Topic :: Software Development :: Build Tools
Classifier: Topic :: Software Development :: Libraries :: Python Modules
Classifier: License :: OSI Approved :: BSD License
Requires-Dist: Mako
Requires-Dist: birdhousebuilder.recipe.conda
Requires-Dist: birdhousebuilder.recipe.nginx
Requires-Dist: birdhousebuilder.recipe.supervisor
Requires-Dist: setuptools
Requires-Dist: zc.buildout
Requires-Dist: zc.recipe.deployment
Provides-Extra: tests
Requires-Dist: zc.buildout; extra == 'tests'
Requires-Dist: zope.testing; extra == 'tests'
